{
  "headline": "\ud83c\udf0d Andrew Tate mentioned 4.1x more than Mark Zuckerberg this week",
  "type": "horizontal_bar",
  "chart_type": "people_race_primary",
  "data": [
    {
      "name": "Andrew Tate",
      "value": 69
    },
    {
      "name": "Mark Zuckerberg",
      "value": 17
    },
    {
      "name": "Jeff Bezos",
      "value": 11
    },
    {
      "name": "Prince Harry",
      "value": 7
    },
    {
      "name": "King Charles",
      "value": 5
    },
    {
      "name": "Elon Musk",
      "value": 4
    },
    {
      "name": "Sam Altman",
      "value": 3
    },
    {
      "name": "Larry Ellison",
      "value": 1
    }
  ],
  "virality_score": 8.117647058823529
}